GameF.py
GameF-1.0.0.dist-info/METADATA
GameF-1.0.0.dist-info/WHEEL
GameF-1.0.0.dist-info/top_level.txt
GameF-1.0.0.dist-info/RECORD
