Metadata-Version: 2.1
Name: GameF
Version: 1.0.0
Summary: You can use this framework to make a game
Author: ChipWang
Author-email: chipwrj@gmail.com
